photo_culling/caching.py
photo_culling/main.py
photo_culling/utils.py
photo_culling/widgets.py
photo_culling-0.1.3.dist-info/METADATA
photo_culling-0.1.3.dist-info/WHEEL
photo_culling-0.1.3.dist-info/entry_points.txt
photo_culling-0.1.3.dist-info/top_level.txt
photo_culling-0.1.3.dist-info/RECORD
