Metadata-Version: 2.4
Name: photo-culling
Version: 0.1.3
Summary: Fast and minimal photo culling tool
Author-email: Michael Scherbela <michael.scherbela@gmail.com>
Requires-Python: >=3.12
Requires-Dist: pillow>=11.1.0
Requires-Dist: pyqt6>=6.9.1
